{
    "data": [
        {
            "all_awardings": [],
            "associated_award": null,
            "author": "Yout60",
            "author_flair_background_color": null,
            "author_flair_css_class": null,
            "author_flair_richtext": [],
            "author_flair_template_id": null,
            "author_flair_text": null,
            "author_flair_text_color": null,
            "author_flair_type": "text",
            "author_fullname": "t2_5lmq4h5z",
            "author_patreon_flair": false,
            "author_premium": false,
            "awarders": [],
            "body": "I'm up",
            "collapsed_because_crowd_control": null,
            "comment_type": null,
            "created_utc": 1610925662,
            "gildings": {},
            "id": "gjnuoaq",
            "is_submitter": false,
            "link_id": "t3_kzh6dh",
            "locked": false,
            "no_follow": true,
            "parent_id": "t3_kzh6dh",
            "permalink": "/r/SexRoleplay/comments/kzh6dh/someone_wants_to_rp/gjnuoaq/",
            "retrieved_on": 1611042033,
            "score": 1,
            "send_replies": true,
            "stickied": false,
            "subreddit": "SexRoleplay",
            "subreddit_id": "t5_2f3amd",
            "top_awarded_type": null,
            "total_awards_received": 0,
            "treatment_tags": []
        },
        {
            "all_awardings": [],
            "associated_award": null,
            "author": "Altafacha",
            "author_flair_background_color": null,
            "author_flair_css_class": null,
            "author_flair_richtext": [],
            "author_flair_template_id": null,
            "author_flair_text": null,
            "author_flair_text_color": null,
            "author_flair_type": "text",
            "author_fullname": "t2_7sgxv755",
            "author_patreon_flair": false,
            "author_premium": false,
            "awarders": [],
            "body": "Sure",
            "collapsed_because_crowd_control": null,
            "comment_type": null,
            "created_utc": 1610926460,
            "gildings": {},
            "id": "gjnw7eo",
            "is_submitter": true,
            "link_id": "t3_kzh6dh",
            "locked": false,
            "no_follow": true,
            "parent_id": "t1_gjnuoaq",
            "permalink": "/r/SexRoleplay/comments/kzh6dh/someone_wants_to_rp/gjnw7eo/",
            "retrieved_on": 1611042889,
            "score": 1,
            "send_replies": true,
            "stickied": false,
            "subreddit": "SexRoleplay",
            "subreddit_id": "t5_2f3amd",
            "top_awarded_type": null,
            "total_awards_received": 0,
            "treatment_tags": []
        },
        {
            "all_awardings": [],
            "associated_award": null,
            "author": "Yout60",
            "author_flair_background_color": null,
            "author_flair_css_class": null,
            "author_flair_richtext": [],
            "author_flair_template_id": null,
            "author_flair_text": null,
            "author_flair_text_color": null,
            "author_flair_type": "text",
            "author_fullname": "t2_5lmq4h5z",
            "author_patreon_flair": false,
            "author_premium": false,
            "awarders": [],
            "body": "Ok so what are your boundaries?",
            "collapsed_because_crowd_control": null,
            "comment_type": null,
            "created_utc": 1610926679,
            "gildings": {},
            "id": "gjnwmfo",
            "is_submitter": false,
            "link_id": "t3_kzh6dh",
            "locked": false,
            "no_follow": true,
            "parent_id": "t3_kzh6dh",
            "permalink": "/r/SexRoleplay/comments/kzh6dh/someone_wants_to_rp/gjnwmfo/",
            "retrieved_on": 1611043124,
            "score": 1,
            "send_replies": true,
            "stickied": false,
            "subreddit": "SexRoleplay",
            "subreddit_id": "t5_2f3amd",
            "top_awarded_type": null,
            "total_awards_received": 0,
            "treatment_tags": []
        },
        {
            "all_awardings": [],
            "associated_award": null,
            "author": "Altafacha",
            "author_flair_background_color": null,
            "author_flair_css_class": null,
            "author_flair_richtext": [],
            "author_flair_template_id": null,
            "author_flair_text": null,
            "author_flair_text_color": null,
            "author_flair_type": "text",
            "author_fullname": "t2_7sgxv755",
            "author_patreon_flair": false,
            "author_premium": false,
            "awarders": [],
            "body": "dm",
            "collapsed_because_crowd_control": null,
            "comment_type": null,
            "created_utc": 1610926724,
            "gildings": {},
            "id": "gjnwpk7",
            "is_submitter": true,
            "link_id": "t3_kzh6dh",
            "locked": false,
            "no_follow": true,
            "parent_id": "t1_gjnwmfo",
            "permalink": "/r/SexRoleplay/comments/kzh6dh/someone_wants_to_rp/gjnwpk7/",
            "retrieved_on": 1611043172,
            "score": 1,
            "send_replies": true,
            "stickied": false,
            "subreddit": "SexRoleplay",
            "subreddit_id": "t5_2f3amd",
            "top_awarded_type": null,
            "total_awards_received": 0,
            "treatment_tags": []
        }
    ]
}