{
    "data": [
        {
            "all_awardings": [],
            "associated_award": null,
            "author": "finmcculloch",
            "author_flair_background_color": null,
            "author_flair_css_class": null,
            "author_flair_richtext": [],
            "author_flair_template_id": null,
            "author_flair_text": null,
            "author_flair_text_color": null,
            "author_flair_type": "text",
            "author_fullname": "t2_8fl6yoe8",
            "author_patreon_flair": false,
            "author_premium": false,
            "awarders": [],
            "body": "Dm me",
            "collapsed_because_crowd_control": null,
            "comment_type": null,
            "created_utc": 1611266165,
            "gildings": {},
            "id": "gk3xbct",
            "is_submitter": false,
            "link_id": "t3_l1tgxt",
            "locked": false,
            "no_follow": true,
            "parent_id": "t3_l1tgxt",
            "permalink": "/r/SexRoleplay/comments/l1tgxt/m4f_sister_returns_home_from_college_and_has/gk3xbct/",
            "retrieved_on": 1611399462,
            "score": 1,
            "send_replies": true,
            "stickied": false,
            "subreddit": "SexRoleplay",
            "subreddit_id": "t5_2f3amd",
            "top_awarded_type": null,
            "total_awards_received": 0,
            "treatment_tags": []
        }
    ]
}