{
    "data": [
        {
            "all_awardings": [],
            "author": "superarmy",
            "author_flair_background_color": null,
            "author_flair_css_class": null,
            "author_flair_richtext": [],
            "author_flair_template_id": null,
            "author_flair_text": null,
            "author_flair_text_color": null,
            "author_flair_type": "text",
            "author_fullname": "t2_64mfn",
            "author_patreon_flair": false,
            "body": "Where abouts in Colorado are you. 28 m. Single 6 ft 1",
            "created_utc": 1562728907,
            "gildings": {},
            "id": "etecpmy",
            "is_submitter": false,
            "link_id": "t3_cbb5ic",
            "locked": false,
            "no_follow": true,
            "parent_id": "t3_cbb5ic",
            "permalink": "/r/dirtyr4r/comments/cbb5ic/23_f4m_colorado_midweek_recharge/etecpmy/",
            "retrieved_on": 1562728909,
            "score": 1,
            "send_replies": true,
            "stickied": false,
            "subreddit": "dirtyr4r",
            "subreddit_id": "t5_2vqun",
            "total_awards_received": 0,
            "updated_utc": 1562832506
        },
        {
            "all_awardings": [],
            "author": "repaidoregano",
            "author_flair_background_color": null,
            "author_flair_css_class": null,
            "author_flair_richtext": [],
            "author_flair_template_id": null,
            "author_flair_text": null,
            "author_flair_text_color": null,
            "author_flair_type": "text",
            "author_fullname": "t2_275jyrga",
            "author_patreon_flair": false,
            "body": "Pm'd you.",
            "created_utc": 1562730475,
            "gildings": {},
            "id": "eteem70",
            "is_submitter": false,
            "link_id": "t3_cbb5ic",
            "locked": false,
            "no_follow": true,
            "parent_id": "t3_cbb5ic",
            "permalink": "/r/dirtyr4r/comments/cbb5ic/23_f4m_colorado_midweek_recharge/eteem70/",
            "retrieved_on": 1562730477,
            "score": -1,
            "send_replies": true,
            "stickied": false,
            "subreddit": "dirtyr4r",
            "subreddit_id": "t5_2vqun",
            "total_awards_received": 0,
            "updated_utc": 1562832956
        },
        {
            "all_awardings": [],
            "author": "Israaaaman",
            "author_flair_background_color": null,
            "author_flair_css_class": null,
            "author_flair_richtext": [],
            "author_flair_template_id": null,
            "author_flair_text": null,
            "author_flair_text_color": null,
            "author_flair_type": "text",
            "author_fullname": "t2_1sxuvzzs",
            "author_patreon_flair": false,
            "body": "Message sent",
            "created_utc": 1562731606,
            "gildings": {},
            "id": "etefxpn",
            "is_submitter": false,
            "link_id": "t3_cbb5ic",
            "locked": false,
            "no_follow": true,
            "parent_id": "t3_cbb5ic",
            "permalink": "/r/dirtyr4r/comments/cbb5ic/23_f4m_colorado_midweek_recharge/etefxpn/",
            "retrieved_on": 1562731607,
            "score": -1,
            "send_replies": true,
            "stickied": false,
            "subreddit": "dirtyr4r",
            "subreddit_id": "t5_2vqun",
            "total_awards_received": 0,
            "updated_utc": 1562833273
        }
    ]
}