{
    "data": [
        {
            "all_awardings": [],
            "associated_award": null,
            "author": "Sakurashi2001",
            "author_flair_background_color": null,
            "author_flair_css_class": null,
            "author_flair_richtext": [],
            "author_flair_template_id": null,
            "author_flair_text": null,
            "author_flair_text_color": null,
            "author_flair_type": "text",
            "author_fullname": "t2_8sxxb6h7",
            "author_patreon_flair": false,
            "author_premium": false,
            "awarders": [],
            "body": "FxT? What does T stand for?",
            "collapsed_because_crowd_control": null,
            "collapsed_reason_code": null,
            "comment_type": null,
            "created_utc": 1635621233,
            "gildings": {},
            "id": "hioecru",
            "is_submitter": false,
            "link_id": "t3_qj848s",
            "locked": false,
            "no_follow": true,
            "parent_id": "t3_qj848s",
            "permalink": "/r/BadRPerStories/comments/qj848s/i_clearly_am_lying_about_my_gender_apparently_o/hioecru/",
            "retrieved_on": 1635822400,
            "score": 2,
            "send_replies": true,
            "stickied": false,
            "subreddit": "BadRPerStories",
            "subreddit_id": "t5_37a22",
            "top_awarded_type": null,
            "total_awards_received": 0,
            "treatment_tags": [],
            "unrepliable_reason": null
        },
        {
            "all_awardings": [],
            "associated_award": null,
            "author": "Electrical-Kick6013",
            "author_flair_background_color": null,
            "author_flair_css_class": null,
            "author_flair_richtext": [],
            "author_flair_template_id": null,
            "author_flair_text": null,
            "author_flair_text_color": null,
            "author_flair_type": "text",
            "author_fullname": "t2_co4xioir",
            "author_patreon_flair": false,
            "author_premium": false,
            "awarders": [],
            "body": "Sounds like the same person I dealt with yesterday lol. I even made a post here about it.",
            "collapsed_because_crowd_control": null,
            "collapsed_reason_code": null,
            "comment_type": null,
            "created_utc": 1635621296,
            "gildings": {},
            "id": "hioehy6",
            "is_submitter": false,
            "link_id": "t3_qj848s",
            "locked": false,
            "no_follow": false,
            "parent_id": "t3_qj848s",
            "permalink": "/r/BadRPerStories/comments/qj848s/i_clearly_am_lying_about_my_gender_apparently_o/hioehy6/",
            "retrieved_on": 1635822486,
            "score": 6,
            "send_replies": true,
            "stickied": false,
            "subreddit": "BadRPerStories",
            "subreddit_id": "t5_37a22",
            "top_awarded_type": null,
            "total_awards_received": 0,
            "treatment_tags": [],
            "unrepliable_reason": null
        },
        {
            "all_awardings": [],
            "associated_award": null,
            "author": "BethieKitty",
            "author_flair_background_color": null,
            "author_flair_css_class": null,
            "author_flair_richtext": [],
            "author_flair_template_id": null,
            "author_flair_text": null,
            "author_flair_text_color": null,
            "author_flair_type": "text",
            "author_fullname": "t2_4sthz0pb",
            "author_patreon_flair": false,
            "author_premium": false,
            "awarders": [],
            "body": "Trans. It is a label in one of the rp groups I'm in.",
            "collapsed_because_crowd_control": null,
            "collapsed_reason_code": null,
            "comment_type": null,
            "created_utc": 1635621338,
            "gildings": {},
            "id": "hioelhi",
            "is_submitter": true,
            "link_id": "t3_qj848s",
            "locked": false,
            "no_follow": true,
            "parent_id": "t1_hioecru",
            "permalink": "/r/BadRPerStories/comments/qj848s/i_clearly_am_lying_about_my_gender_apparently_o/hioelhi/",
            "retrieved_on": 1635822543,
            "score": 1,
            "send_replies": true,
            "stickied": false,
            "subreddit": "BadRPerStories",
            "subreddit_id": "t5_37a22",
            "top_awarded_type": null,
            "total_awards_received": 0,
            "treatment_tags": [],
            "unrepliable_reason": null
        },
        {
            "all_awardings": [],
            "associated_award": null,
            "author": "BethieKitty",
            "author_flair_background_color": null,
            "author_flair_css_class": null,
            "author_flair_richtext": [],
            "author_flair_template_id": null,
            "author_flair_text": null,
            "author_flair_text_color": null,
            "author_flair_type": "text",
            "author_fullname": "t2_4sthz0pb",
            "author_patreon_flair": false,
            "author_premium": false,
            "awarders": [],
            "body": "I had the dude this morning XD I was barely awake yet. It was 8 am for me and I was waking up to feed the cats and got hit with all that. Not today satan... not today XD hate people like that. Why does my RL gender matter if I am role-playing a CHARACTER with you lmfao",
            "collapsed_because_crowd_control": null,
            "collapsed_reason_code": null,
            "comment_type": null,
            "created_utc": 1635621432,
            "gildings": {},
            "id": "hioet4c",
            "is_submitter": true,
            "link_id": "t3_qj848s",
            "locked": false,
            "no_follow": false,
            "parent_id": "t1_hioehy6",
            "permalink": "/r/BadRPerStories/comments/qj848s/i_clearly_am_lying_about_my_gender_apparently_o/hioet4c/",
            "retrieved_on": 1635822668,
            "score": 6,
            "send_replies": true,
            "stickied": false,
            "subreddit": "BadRPerStories",
            "subreddit_id": "t5_37a22",
            "top_awarded_type": null,
            "total_awards_received": 0,
            "treatment_tags": [],
            "unrepliable_reason": null
        },
        {
            "all_awardings": [],
            "associated_award": null,
            "author": "Sakurashi2001",
            "author_flair_background_color": null,
            "author_flair_css_class": null,
            "author_flair_richtext": [],
            "author_flair_template_id": null,
            "author_flair_text": null,
            "author_flair_text_color": null,
            "author_flair_type": "text",
            "author_fullname": "t2_8sxxb6h7",
            "author_patreon_flair": false,
            "author_premium": false,
            "awarders": [],
            "body": "But why? Trans only means that one is a man, woman or non binary, not an extra gender. It is also unspecific. Do you mean a trans man, trans woman or something else? How would you use that when searching for a partner?",
            "collapsed_because_crowd_control": null,
            "collapsed_reason_code": null,
            "comment_type": null,
            "created_utc": 1635621527,
            "gildings": {},
            "id": "hiof0uo",
            "is_submitter": false,
            "link_id": "t3_qj848s",
            "locked": false,
            "no_follow": false,
            "parent_id": "t1_hioelhi",
            "permalink": "/r/BadRPerStories/comments/qj848s/i_clearly_am_lying_about_my_gender_apparently_o/hiof0uo/",
            "retrieved_on": 1635822797,
            "score": 5,
            "send_replies": true,
            "stickied": false,
            "subreddit": "BadRPerStories",
            "subreddit_id": "t5_37a22",
            "top_awarded_type": null,
            "total_awards_received": 0,
            "treatment_tags": [],
            "unrepliable_reason": null
        },
        {
            "all_awardings": [],
            "associated_award": null,
            "author": "Electrical-Kick6013",
            "author_flair_background_color": null,
            "author_flair_css_class": null,
            "author_flair_richtext": [],
            "author_flair_template_id": null,
            "author_flair_text": null,
            "author_flair_text_color": null,
            "author_flair_type": "text",
            "author_fullname": "t2_co4xioir",
            "author_patreon_flair": false,
            "author_premium": false,
            "awarders": [],
            "body": "Honestly... The whole point of roleplaying is usually to play as a character in set circumstances. Personal IRL stuff don't matter.",
            "collapsed_because_crowd_control": null,
            "collapsed_reason_code": null,
            "comment_type": null,
            "created_utc": 1635621540,
            "gildings": {},
            "id": "hiof1ye",
            "is_submitter": false,
            "link_id": "t3_qj848s",
            "locked": false,
            "no_follow": false,
            "parent_id": "t1_hioet4c",
            "permalink": "/r/BadRPerStories/comments/qj848s/i_clearly_am_lying_about_my_gender_apparently_o/hiof1ye/",
            "retrieved_on": 1635822816,
            "score": 6,
            "send_replies": true,
            "stickied": false,
            "subreddit": "BadRPerStories",
            "subreddit_id": "t5_37a22",
            "top_awarded_type": null,
            "total_awards_received": 0,
            "treatment_tags": [],
            "unrepliable_reason": null
        },
        {
            "all_awardings": [],
            "associated_award": null,
            "author": "throawaymcdumbface",
            "author_flair_background_color": null,
            "author_flair_css_class": null,
            "author_flair_richtext": [],
            "author_flair_template_id": null,
            "author_flair_text": null,
            "author_flair_text_color": null,
            "author_flair_type": "text",
            "author_fullname": "t2_l4ptlvm",
            "author_patreon_flair": false,
            "author_premium": false,
            "awarders": [],
            "body": "Piss-poor bait attempt at making sure you were a 'girl irl' because they wanna be a lineblurring pain in the ass, I'd flag it to the board.\n\nI think guys legit don't get \"you have to be a girl irl\" as prerequisite = mmmmost women are gonna avoid the fuck out of you because it's clear its being done for 'ew gay also I want to hit on the player' reasons.",
            "collapsed_because_crowd_control": null,
            "collapsed_reason_code": null,
            "comment_type": null,
            "created_utc": 1635621627,
            "gildings": {},
            "id": "hiof92c",
            "is_submitter": false,
            "link_id": "t3_qj848s",
            "locked": false,
            "no_follow": false,
            "parent_id": "t3_qj848s",
            "permalink": "/r/BadRPerStories/comments/qj848s/i_clearly_am_lying_about_my_gender_apparently_o/hiof92c/",
            "retrieved_on": 1635822937,
            "score": 38,
            "send_replies": true,
            "stickied": false,
            "subreddit": "BadRPerStories",
            "subreddit_id": "t5_37a22",
            "top_awarded_type": null,
            "total_awards_received": 0,
            "treatment_tags": [],
            "unrepliable_reason": null
        },
        {
            "all_awardings": [],
            "associated_award": null,
            "author": "BethieKitty",
            "author_flair_background_color": null,
            "author_flair_css_class": null,
            "author_flair_richtext": [],
            "author_flair_template_id": null,
            "author_flair_text": null,
            "author_flair_text_color": null,
            "author_flair_type": "text",
            "author_fullname": "t2_4sthz0pb",
            "author_patreon_flair": false,
            "author_premium": false,
            "awarders": [],
            "body": "I just considered it meaning trans character. I don't really care what type of trans the character is. They just put the label in because they had someone get uppity over people playing trans characters.",
            "collapsed_because_crowd_control": null,
            "collapsed_reason_code": null,
            "comment_type": null,
            "created_utc": 1635621660,
            "gildings": {},
            "id": "hiofbqw",
            "is_submitter": true,
            "link_id": "t3_qj848s",
            "locked": false,
            "no_follow": false,
            "parent_id": "t1_hiof0uo",
            "permalink": "/r/BadRPerStories/comments/qj848s/i_clearly_am_lying_about_my_gender_apparently_o/hiofbqw/",
            "retrieved_on": 1635822983,
            "score": 3,
            "send_replies": true,
            "stickied": false,
            "subreddit": "BadRPerStories",
            "subreddit_id": "t5_37a22",
            "top_awarded_type": null,
            "total_awards_received": 0,
            "treatment_tags": [],
            "unrepliable_reason": null
        },
        {
            "all_awardings": [],
            "associated_award": null,
            "author": "BethieKitty",
            "author_flair_background_color": null,
            "author_flair_css_class": null,
            "author_flair_richtext": [],
            "author_flair_template_id": null,
            "author_flair_text": null,
            "author_flair_text_color": null,
            "author_flair_type": "text",
            "author_fullname": "t2_4sthz0pb",
            "author_patreon_flair": false,
            "author_premium": false,
            "awarders": [],
            "body": "Right... I am married I don't have to prove my gender to any one especially not some creep who \"only rps with REAL WOMENS\" lol",
            "collapsed_because_crowd_control": null,
            "collapsed_reason_code": null,
            "comment_type": null,
            "created_utc": 1635621747,
            "gildings": {},
            "id": "hiofizb",
            "is_submitter": true,
            "link_id": "t3_qj848s",
            "locked": false,
            "no_follow": false,
            "parent_id": "t1_hiof92c",
            "permalink": "/r/BadRPerStories/comments/qj848s/i_clearly_am_lying_about_my_gender_apparently_o/hiofizb/",
            "retrieved_on": 1635823103,
            "score": 6,
            "send_replies": true,
            "stickied": false,
            "subreddit": "BadRPerStories",
            "subreddit_id": "t5_37a22",
            "top_awarded_type": null,
            "total_awards_received": 0,
            "treatment_tags": [],
            "unrepliable_reason": null
        },
        {
            "all_awardings": [],
            "associated_award": null,
            "author": "throawaymcdumbface",
            "author_flair_background_color": null,
            "author_flair_css_class": null,
            "author_flair_richtext": [],
            "author_flair_template_id": null,
            "author_flair_text": null,
            "author_flair_text_color": null,
            "author_flair_type": "text",
            "author_fullname": "t2_l4ptlvm",
            "author_patreon_flair": false,
            "author_premium": false,
            "awarders": [],
            "body": "did their name start with a roman numerical?",
            "collapsed_because_crowd_control": null,
            "collapsed_reason_code": null,
            "comment_type": null,
            "created_utc": 1635622067,
            "gildings": {},
            "id": "hiog91a",
            "is_submitter": false,
            "link_id": "t3_qj848s",
            "locked": false,
            "no_follow": false,
            "parent_id": "t1_hioet4c",
            "permalink": "/r/BadRPerStories/comments/qj848s/i_clearly_am_lying_about_my_gender_apparently_o/hiog91a/",
            "retrieved_on": 1635823544,
            "score": 4,
            "send_replies": true,
            "stickied": false,
            "subreddit": "BadRPerStories",
            "subreddit_id": "t5_37a22",
            "top_awarded_type": null,
            "total_awards_received": 0,
            "treatment_tags": [],
            "unrepliable_reason": null
        },
        {
            "all_awardings": [],
            "associated_award": null,
            "author": "BethieKitty",
            "author_flair_background_color": null,
            "author_flair_css_class": null,
            "author_flair_richtext": [],
            "author_flair_template_id": null,
            "author_flair_text": null,
            "author_flair_text_color": null,
            "author_flair_type": "text",
            "author_fullname": "t2_4sthz0pb",
            "author_patreon_flair": false,
            "author_premium": false,
            "awarders": [],
            "body": "No his name had a Naruto character at the beginning with POG after it. Whatever pog means XD",
            "collapsed_because_crowd_control": null,
            "collapsed_reason_code": null,
            "comment_type": null,
            "created_utc": 1635622697,
            "gildings": {},
            "id": "hiohoz8",
            "is_submitter": true,
            "link_id": "t3_qj848s",
            "locked": false,
            "no_follow": false,
            "parent_id": "t1_hiog91a",
            "permalink": "/r/BadRPerStories/comments/qj848s/i_clearly_am_lying_about_my_gender_apparently_o/hiohoz8/",
            "retrieved_on": 1635824385,
            "score": 6,
            "send_replies": true,
            "stickied": false,
            "subreddit": "BadRPerStories",
            "subreddit_id": "t5_37a22",
            "top_awarded_type": null,
            "total_awards_received": 0,
            "treatment_tags": [],
            "unrepliable_reason": null
        },
        {
            "all_awardings": [],
            "associated_award": null,
            "author": "mssMouse",
            "author_flair_background_color": null,
            "author_flair_css_class": null,
            "author_flair_richtext": [],
            "author_flair_template_id": null,
            "author_flair_text": null,
            "author_flair_text_color": null,
            "author_flair_type": "text",
            "author_fullname": "t2_6di23e7n",
            "author_patreon_flair": false,
            "author_premium": false,
            "awarders": [],
            "body": "While I see your point, it's just an extra identifier because it could be possible someone would not be interested in playing against a trans character (valid reasoning or not)... Although yeah, it does lack specification, I think it lets someone know that they're open to it.\n\nLike, I specify I'm up for playing transwomen. \n\nI'm sure if someone puts FxT and someone is unsure if the T would be transman or transwoman, they can simply ask.",
            "collapsed_because_crowd_control": null,
            "collapsed_reason_code": null,
            "comment_type": null,
            "created_utc": 1635623157,
            "gildings": {},
            "id": "hioiqp3",
            "is_submitter": false,
            "link_id": "t3_qj848s",
            "locked": false,
            "no_follow": true,
            "parent_id": "t1_hiof0uo",
            "permalink": "/r/BadRPerStories/comments/qj848s/i_clearly_am_lying_about_my_gender_apparently_o/hioiqp3/",
            "retrieved_on": 1635824983,
            "score": 2,
            "send_replies": true,
            "stickied": false,
            "subreddit": "BadRPerStories",
            "subreddit_id": "t5_37a22",
            "top_awarded_type": null,
            "total_awards_received": 0,
            "treatment_tags": [],
            "unrepliable_reason": null
        },
        {
            "all_awardings": [],
            "associated_award": null,
            "author": "AestheticMuffin",
            "author_flair_background_color": null,
            "author_flair_css_class": null,
            "author_flair_richtext": [],
            "author_flair_template_id": null,
            "author_flair_text": null,
            "author_flair_text_color": null,
            "author_flair_type": "text",
            "author_fullname": "t2_9n6w7f98",
            "author_patreon_flair": false,
            "author_premium": false,
            "awarders": [],
            "body": "Ok, but real talk. WTF is up with some guys thinking you're catfishing them on the internet and that you're not a real woman in completely non-romantic / not dating situations? I haven't had this happen to me in a while, but back when I used to do gaming there was always at least one dude whose like \"HMMM I DON'T THINK YOU'RE REAL\" and would want me to either a.) speak on mic or b.) send them a pic.\n\nit's super weird and honestly creepy.",
            "collapsed_because_crowd_control": null,
            "collapsed_reason_code": null,
            "comment_type": null,
            "created_utc": 1635623671,
            "gildings": {},
            "id": "hiojxwf",
            "is_submitter": false,
            "link_id": "t3_qj848s",
            "locked": false,
            "no_follow": false,
            "parent_id": "t3_qj848s",
            "permalink": "/r/BadRPerStories/comments/qj848s/i_clearly_am_lying_about_my_gender_apparently_o/hiojxwf/",
            "retrieved_on": 1635825653,
            "score": 16,
            "send_replies": true,
            "stickied": false,
            "subreddit": "BadRPerStories",
            "subreddit_id": "t5_37a22",
            "top_awarded_type": null,
            "total_awards_received": 0,
            "treatment_tags": [],
            "unrepliable_reason": null
        },
        {
            "all_awardings": [],
            "associated_award": null,
            "author": "BethieKitty",
            "author_flair_background_color": null,
            "author_flair_css_class": null,
            "author_flair_richtext": [],
            "author_flair_template_id": null,
            "author_flair_text": null,
            "author_flair_text_color": null,
            "author_flair_type": "text",
            "author_fullname": "t2_4sthz0pb",
            "author_patreon_flair": false,
            "author_premium": false,
            "awarders": [],
            "body": "It IS very creepy! Showed all that to my husband and he was like... wtf even is that guy and told me I should have asked if he was a real man XD",
            "collapsed_because_crowd_control": null,
            "collapsed_reason_code": null,
            "comment_type": null,
            "created_utc": 1635623840,
            "gildings": {},
            "id": "hiokc0e",
            "is_submitter": true,
            "link_id": "t3_qj848s",
            "locked": false,
            "no_follow": false,
            "parent_id": "t1_hiojxwf",
            "permalink": "/r/BadRPerStories/comments/qj848s/i_clearly_am_lying_about_my_gender_apparently_o/hiokc0e/",
            "retrieved_on": 1635825871,
            "score": 7,
            "send_replies": true,
            "stickied": false,
            "subreddit": "BadRPerStories",
            "subreddit_id": "t5_37a22",
            "top_awarded_type": null,
            "total_awards_received": 0,
            "treatment_tags": [],
            "unrepliable_reason": null
        },
        {
            "all_awardings": [],
            "associated_award": null,
            "author": "BethieKitty",
            "author_flair_background_color": null,
            "author_flair_css_class": null,
            "author_flair_richtext": [],
            "author_flair_template_id": null,
            "author_flair_text": null,
            "author_flair_text_color": null,
            "author_flair_type": "text",
            "author_fullname": "t2_4sthz0pb",
            "author_patreon_flair": false,
            "author_premium": false,
            "awarders": [],
            "body": "Exactly ^_^ I'm fine with either but others might have a preference. It was put in place to show that we are fine playing with people who play trans characters because some folks had been hateful about those who played trans characters. The people that were hateful over it were removed though thank goodness cause I saw one myself freak in general chat saying some very hurtful stuff",
            "collapsed_because_crowd_control": null,
            "collapsed_reason_code": null,
            "comment_type": null,
            "created_utc": 1635623968,
            "gildings": {},
            "id": "hiokmmi",
            "is_submitter": true,
            "link_id": "t3_qj848s",
            "locked": false,
            "no_follow": true,
            "parent_id": "t1_hioiqp3",
            "permalink": "/r/BadRPerStories/comments/qj848s/i_clearly_am_lying_about_my_gender_apparently_o/hiokmmi/",
            "retrieved_on": 1635826033,
            "score": 2,
            "send_replies": true,
            "stickied": false,
            "subreddit": "BadRPerStories",
            "subreddit_id": "t5_37a22",
            "top_awarded_type": null,
            "total_awards_received": 0,
            "treatment_tags": [],
            "unrepliable_reason": null
        },
        {
            "all_awardings": [],
            "associated_award": null,
            "author": "SoftGalaxies",
            "author_flair_background_color": null,
            "author_flair_css_class": null,
            "author_flair_richtext": [],
            "author_flair_template_id": null,
            "author_flair_text": null,
            "author_flair_text_color": null,
            "author_flair_type": "text",
            "author_fullname": "t2_dnt97y0r",
            "author_patreon_flair": false,
            "author_premium": false,
            "awarders": [],
            "body": "Pog/Poggers was coined over on Twitch. It originally meant/means \u201cPlay of the Game\u201d it\u2019s typically also used to just express excitement. Hope that helps! ^^\n\nAnd honestly that person sounds like a nightmare and/or dumber than a pile of bricks.",
            "collapsed_because_crowd_control": null,
            "collapsed_reason_code": null,
            "comment_type": null,
            "created_utc": 1635623970,
            "gildings": {},
            "id": "hiokmr2",
            "is_submitter": false,
            "link_id": "t3_qj848s",
            "locked": false,
            "no_follow": false,
            "parent_id": "t1_hiohoz8",
            "permalink": "/r/BadRPerStories/comments/qj848s/i_clearly_am_lying_about_my_gender_apparently_o/hiokmr2/",
            "retrieved_on": 1635826034,
            "score": 7,
            "send_replies": true,
            "stickied": false,
            "subreddit": "BadRPerStories",
            "subreddit_id": "t5_37a22",
            "top_awarded_type": null,
            "total_awards_received": 0,
            "treatment_tags": [],
            "unrepliable_reason": null
        },
        {
            "all_awardings": [],
            "associated_award": null,
            "author": "BethieKitty",
            "author_flair_background_color": null,
            "author_flair_css_class": null,
            "author_flair_richtext": [],
            "author_flair_template_id": null,
            "author_flair_text": null,
            "author_flair_text_color": null,
            "author_flair_type": "text",
            "author_fullname": "t2_4sthz0pb",
            "author_patreon_flair": false,
            "author_premium": false,
            "awarders": [],
            "body": "Thank you so much! I stream on twitch and have heard it but never asked what it meant lol. ^_^ now I know. And yeah he absolutely was a nightmare.",
            "collapsed_because_crowd_control": null,
            "collapsed_reason_code": null,
            "comment_type": null,
            "created_utc": 1635624052,
            "gildings": {},
            "id": "hioktib",
            "is_submitter": true,
            "link_id": "t3_qj848s",
            "locked": false,
            "no_follow": true,
            "parent_id": "t1_hiokmr2",
            "permalink": "/r/BadRPerStories/comments/qj848s/i_clearly_am_lying_about_my_gender_apparently_o/hioktib/",
            "retrieved_on": 1635826138,
            "score": 3,
            "send_replies": true,
            "stickied": false,
            "subreddit": "BadRPerStories",
            "subreddit_id": "t5_37a22",
            "top_awarded_type": null,
            "total_awards_received": 0,
            "treatment_tags": [],
            "unrepliable_reason": null
        },
        {
            "all_awardings": [],
            "associated_award": null,
            "author": "Sakurashi2001",
            "author_flair_background_color": null,
            "author_flair_css_class": null,
            "author_flair_richtext": [],
            "author_flair_template_id": null,
            "author_flair_text": null,
            "author_flair_text_color": null,
            "author_flair_type": "text",
            "author_fullname": "t2_8sxxb6h7",
            "author_patreon_flair": false,
            "author_premium": false,
            "awarders": [],
            "body": "Or you could specify by using TF or TM. I think it is a bit weird to only state that they have transitioned. Nobody says they are searching for a cis person. Most people say that they want to play against a man, a woman or that anything is fine.",
            "collapsed_because_crowd_control": null,
            "collapsed_reason_code": null,
            "comment_type": null,
            "created_utc": 1635624183,
            "gildings": {},
            "id": "hiol41y",
            "is_submitter": false,
            "link_id": "t3_qj848s",
            "locked": false,
            "no_follow": false,
            "parent_id": "t1_hioiqp3",
            "permalink": "/r/BadRPerStories/comments/qj848s/i_clearly_am_lying_about_my_gender_apparently_o/hiol41y/",
            "retrieved_on": 1635826303,
            "score": 4,
            "send_replies": true,
            "stickied": false,
            "subreddit": "BadRPerStories",
            "subreddit_id": "t5_37a22",
            "top_awarded_type": null,
            "total_awards_received": 0,
            "treatment_tags": [],
            "unrepliable_reason": null
        },
        {
            "all_awardings": [],
            "associated_award": null,
            "author": "AGirlHasNoName2018",
            "author_flair_background_color": null,
            "author_flair_css_class": null,
            "author_flair_richtext": [],
            "author_flair_template_id": null,
            "author_flair_text": null,
            "author_flair_text_color": null,
            "author_flair_type": "text",
            "author_fullname": "t2_3p9kh30b",
            "author_patreon_flair": false,
            "author_premium": false,
            "awarders": [],
            "body": "I, a woman, play men and women equally. I don\u2019t understand people who don\u2019t \u201cget\u201d that. RP is fantasy, I can be anyone I want to be and sometimes I want to write men. Also, someone that demanding and aggressive and weird in the first few messages isn\u2019t someone I want to RP with anyway.\n\nMaybe the woman won\u2019t gladly send a pic because she doesn\u2019t want to end up in your spank bank my dude.",
            "collapsed_because_crowd_control": null,
            "collapsed_reason_code": null,
            "comment_type": null,
            "created_utc": 1635625061,
            "gildings": {},
            "id": "hion2me",
            "is_submitter": false,
            "link_id": "t3_qj848s",
            "locked": false,
            "no_follow": false,
            "parent_id": "t3_qj848s",
            "permalink": "/r/BadRPerStories/comments/qj848s/i_clearly_am_lying_about_my_gender_apparently_o/hion2me/",
            "retrieved_on": 1635827429,
            "score": 10,
            "send_replies": true,
            "stickied": false,
            "subreddit": "BadRPerStories",
            "subreddit_id": "t5_37a22",
            "top_awarded_type": null,
            "total_awards_received": 0,
            "treatment_tags": [],
            "unrepliable_reason": null
        },
        {
            "all_awardings": [],
            "associated_award": null,
            "author": "BethieKitty",
            "author_flair_background_color": null,
            "author_flair_css_class": null,
            "author_flair_richtext": [],
            "author_flair_template_id": null,
            "author_flair_text": null,
            "author_flair_text_color": null,
            "author_flair_type": "text",
            "author_fullname": "t2_4sthz0pb",
            "author_patreon_flair": false,
            "author_premium": false,
            "awarders": [],
            "body": "Exactly! It is RP why would I wanna play boring human women all the time just because I am one? That guy was weird AF. Bad vibes right off. He will start buried forever in my block list",
            "collapsed_because_crowd_control": null,
            "collapsed_reason_code": null,
            "comment_type": null,
            "created_utc": 1635625685,
            "gildings": {},
            "id": "hioog45",
            "is_submitter": true,
            "link_id": "t3_qj848s",
            "locked": false,
            "no_follow": false,
            "parent_id": "t1_hion2me",
            "permalink": "/r/BadRPerStories/comments/qj848s/i_clearly_am_lying_about_my_gender_apparently_o/hioog45/",
            "retrieved_on": 1635828191,
            "score": 3,
            "send_replies": true,
            "stickied": false,
            "subreddit": "BadRPerStories",
            "subreddit_id": "t5_37a22",
            "top_awarded_type": null,
            "total_awards_received": 0,
            "treatment_tags": [],
            "unrepliable_reason": null
        },
        {
            "all_awardings": [],
            "archived": false,
            "associated_award": null,
            "author": "86sleepypenguins",
            "author_flair_background_color": null,
            "author_flair_css_class": null,
            "author_flair_richtext": [],
            "author_flair_template_id": null,
            "author_flair_text": null,
            "author_flair_text_color": null,
            "author_flair_type": "text",
            "author_fullname": "t2_942s8tt",
            "author_patreon_flair": false,
            "author_premium": false,
            "body": "&gt; Only a man would play a man character.... you can't be a woman no way.\n\nMe, a woman that's been playing almost nothing but male characters for the last ten years: guess I'm a man now \ud83d\ude14\n\nBut seriously, people that do this are so creepy.",
            "body_sha1": "a7416b85dc96ef17aea97b226230e8e0930e45f0",
            "can_gild": true,
            "collapsed": false,
            "collapsed_because_crowd_control": null,
            "collapsed_reason": null,
            "collapsed_reason_code": null,
            "comment_type": null,
            "controversiality": 0,
            "created_utc": 1635625688,
            "distinguished": null,
            "gilded": 0,
            "gildings": {},
            "id": "hioogcl",
            "is_submitter": false,
            "link_id": "t3_qj848s",
            "locked": false,
            "no_follow": true,
            "parent_id": "t3_qj848s",
            "permalink": "/r/BadRPerStories/comments/qj848s/i_clearly_am_lying_about_my_gender_apparently_o/hioogcl/",
            "retrieved_utc": 1635625699,
            "score": 1,
            "score_hidden": true,
            "send_replies": true,
            "stickied": false,
            "subreddit": "BadRPerStories",
            "subreddit_id": "t5_37a22",
            "subreddit_name_prefixed": "r/BadRPerStories",
            "subreddit_type": "public",
            "top_awarded_type": null,
            "total_awards_received": 0,
            "treatment_tags": [],
            "unrepliable_reason": null
        },
        {
            "all_awardings": [],
            "associated_award": null,
            "author": "Irohsgranddaughter",
            "author_flair_background_color": null,
            "author_flair_css_class": null,
            "author_flair_richtext": [],
            "author_flair_template_id": null,
            "author_flair_text": null,
            "author_flair_text_color": null,
            "author_flair_type": "text",
            "author_fullname": "t2_1620gjef",
            "author_patreon_flair": false,
            "author_premium": true,
            "awarders": [],
            "body": "Tbh part of the reason I am myself far more likely to DM a male roleplayer if his ad is M4A rather than M4F.",
            "collapsed_because_crowd_control": null,
            "collapsed_reason_code": null,
            "comment_type": null,
            "created_utc": 1635625723,
            "gildings": {},
            "id": "hiooj19",
            "is_submitter": false,
            "link_id": "t3_qj848s",
            "locked": false,
            "no_follow": false,
            "parent_id": "t3_qj848s",
            "permalink": "/r/BadRPerStories/comments/qj848s/i_clearly_am_lying_about_my_gender_apparently_o/hiooj19/",
            "retrieved_on": 1635828234,
            "score": 8,
            "send_replies": true,
            "stickied": false,
            "subreddit": "BadRPerStories",
            "subreddit_id": "t5_37a22",
            "top_awarded_type": null,
            "total_awards_received": 0,
            "treatment_tags": [],
            "unrepliable_reason": null
        },
        {
            "all_awardings": [],
            "associated_award": null,
            "author": "Mission_Ear_28367",
            "author_flair_background_color": null,
            "author_flair_css_class": null,
            "author_flair_richtext": [],
            "author_flair_template_id": null,
            "author_flair_text": null,
            "author_flair_text_color": null,
            "author_flair_type": "text",
            "author_fullname": "t2_8dx2ye7h",
            "author_patreon_flair": false,
            "author_premium": false,
            "awarders": [],
            "body": "In gaming in particular, at least for MMOs, I thiiiiink (but might still be wrong) it comes from the fact that at one point guys pretending to be women in order to receive free in-game stuff was a wide-spread thing. Wide-spread enough that a plenty of boys in my primary school did it and showed off the stuff their 'e-boyfriends' gave to them the day before. It left some people incredibly wary. Not that I'm saying the ridiculous trend of asking for 'proof' in situations that have nothing to do with dating is valid and justified, but at least that's potentially where it came form.",
            "collapsed_because_crowd_control": null,
            "collapsed_reason_code": null,
            "comment_type": null,
            "created_utc": 1635626299,
            "gildings": {},
            "id": "hiopsw0",
            "is_submitter": false,
            "link_id": "t3_qj848s",
            "locked": false,
            "no_follow": false,
            "parent_id": "t1_hiojxwf",
            "permalink": "/r/BadRPerStories/comments/qj848s/i_clearly_am_lying_about_my_gender_apparently_o/hiopsw0/",
            "retrieved_on": 1635828912,
            "score": 6,
            "send_replies": true,
            "stickied": false,
            "subreddit": "BadRPerStories",
            "subreddit_id": "t5_37a22",
            "top_awarded_type": null,
            "total_awards_received": 0,
            "treatment_tags": [],
            "unrepliable_reason": null
        },
        {
            "all_awardings": [],
            "associated_award": null,
            "author": "mssMouse",
            "author_flair_background_color": null,
            "author_flair_css_class": null,
            "author_flair_richtext": [],
            "author_flair_template_id": null,
            "author_flair_text": null,
            "author_flair_text_color": null,
            "author_flair_type": "text",
            "author_fullname": "t2_6di23e7n",
            "author_patreon_flair": false,
            "author_premium": false,
            "awarders": [],
            "body": "I mean. If the character has, or has not transitioned, the character being trans COULD affect the story beats. (or it could not be something that affects much)\n\nI think it's just a sign that says, \"Hey I'm fine with trans characters\"\n\nBut specifying TF or TM could work too. I don't see why not. But I also don't see why specifying you like writing with trans characters is an issue either. \n\nIf I got a trans character I specifically want to play, then seeing someone in their ad saying \" MxT\", then I can be like, Oh! My character I wanna play could work for this.   \nBut if it's just like MxF or whatever, and I may have to ask, \"Hey the character I wanna play is trans, is that okay?\" And well. Okay yeah doesn't hurt to ask. But at least with the first person, I know from the get-go, they're cool with it. \n\nIt just means they're chill with trans characters. If they wanna say TF or TM, then cool too I guess.",
            "collapsed_because_crowd_control": null,
            "collapsed_reason_code": null,
            "comment_type": null,
            "created_utc": 1635626833,
            "gildings": {},
            "id": "hior0tj",
            "is_submitter": false,
            "link_id": "t3_qj848s",
            "locked": false,
            "no_follow": true,
            "parent_id": "t1_hiol41y",
            "permalink": "/r/BadRPerStories/comments/qj848s/i_clearly_am_lying_about_my_gender_apparently_o/hior0tj/",
            "retrieved_on": 1635829574,
            "score": 1,
            "send_replies": true,
            "stickied": false,
            "subreddit": "BadRPerStories",
            "subreddit_id": "t5_37a22",
            "top_awarded_type": null,
            "total_awards_received": 0,
            "treatment_tags": [],
            "unrepliable_reason": null
        },
        {
            "all_awardings": [],
            "associated_award": null,
            "author": "mssMouse",
            "author_flair_background_color": null,
            "author_flair_css_class": null,
            "author_flair_richtext": [],
            "author_flair_template_id": null,
            "author_flair_text": null,
            "author_flair_text_color": null,
            "author_flair_type": "text",
            "author_fullname": "t2_6di23e7n",
            "author_patreon_flair": false,
            "author_premium": false,
            "awarders": [],
            "body": "For me it's an instant sign that says, \"Sweet, I can play this particular character then with this person\" and don't have to worry about awkward encounters of asking someone, \"hey is it okay if my character is trans?\"\n\nWhich, could be a simple \"no, sorry\", or could turn into something as you've stated, someone starts being hateful.",
            "collapsed_because_crowd_control": null,
            "collapsed_reason_code": null,
            "comment_type": null,
            "created_utc": 1635627133,
            "gildings": {},
            "id": "hiorp62",
            "is_submitter": false,
            "link_id": "t3_qj848s",
            "locked": false,
            "no_follow": true,
            "parent_id": "t1_hiokmmi",
            "permalink": "/r/BadRPerStories/comments/qj848s/i_clearly_am_lying_about_my_gender_apparently_o/hiorp62/",
            "retrieved_on": 1635829943,
            "score": 2,
            "send_replies": true,
            "stickied": false,
            "subreddit": "BadRPerStories",
            "subreddit_id": "t5_37a22",
            "top_awarded_type": null,
            "total_awards_received": 0,
            "treatment_tags": [],
            "unrepliable_reason": null
        }
    ]
}