{
    "data": [
        {
            "author": "outatime81",
            "author_created_utc": 1525545324,
            "author_flair_background_color": null,
            "author_flair_css_class": null,
            "author_flair_richtext": [],
            "author_flair_template_id": null,
            "author_flair_text": null,
            "author_flair_text_color": null,
            "author_flair_type": "text",
            "author_fullname": "t2_1bau6d5x",
            "body": "Damn that turned me on!  Such a hot scenario. ",
            "can_gild": true,
            "collapsed": false,
            "collapsed_reason": null,
            "controversiality": 0,
            "created_utc": 1533551640,
            "distinguished": null,
            "gilded": 0,
            "id": "e3p080b",
            "is_submitter": false,
            "link_id": "t3_94zuud",
            "nest_level": 1,
            "no_follow": true,
            "parent_id": "t3_94zuud",
            "permalink": "/r/dirtypenpals/comments/94zuud/22_f4m_your_girlfriend_doesnt_let_you_well_i_could/e3p080b/",
            "reply_delay": 3700,
            "retrieved_on": 1537132106,
            "score": 1,
            "send_replies": true,
            "stickied": false,
            "subreddit": "dirtypenpals",
            "subreddit_id": "t5_2sbbv",
            "subreddit_name_prefixed": "r/dirtypenpals",
            "subreddit_type": "public"
        },
        {
            "author": "1petter",
            "author_created_utc": 1479130684,
            "author_flair_background_color": null,
            "author_flair_css_class": null,
            "author_flair_richtext": [],
            "author_flair_template_id": null,
            "author_flair_text": null,
            "author_flair_text_color": null,
            "author_flair_type": "text",
            "author_fullname": "t2_12t2ur",
            "body": "\ud83d\ude2ehow did you create this kink list?",
            "can_gild": true,
            "collapsed": false,
            "collapsed_reason": null,
            "controversiality": 0,
            "created_utc": 1533553980,
            "distinguished": null,
            "gilded": 0,
            "id": "e3p1h2r",
            "is_submitter": false,
            "link_id": "t3_94zuud",
            "nest_level": 1,
            "no_follow": true,
            "parent_id": "t3_94zuud",
            "permalink": "/r/dirtypenpals/comments/94zuud/22_f4m_your_girlfriend_doesnt_let_you_well_i_could/e3p1h2r/",
            "reply_delay": 6040,
            "retrieved_on": 1537132691,
            "score": 1,
            "send_replies": true,
            "stickied": false,
            "subreddit": "dirtypenpals",
            "subreddit_id": "t5_2sbbv",
            "subreddit_name_prefixed": "r/dirtypenpals",
            "subreddit_type": "public"
        },
        {
            "author": "DishonestDancing",
            "author_created_utc": 1512719051,
            "author_flair_background_color": null,
            "author_flair_css_class": null,
            "author_flair_richtext": [],
            "author_flair_template_id": null,
            "author_flair_text": null,
            "author_flair_text_color": null,
            "author_flair_type": "text",
            "author_fullname": "t2_nipj82t",
            "body": "I did this with a friend once... so hot. Love girls like you",
            "can_gild": true,
            "collapsed": false,
            "collapsed_reason": null,
            "controversiality": 0,
            "created_utc": 1533555695,
            "distinguished": null,
            "gilded": 0,
            "id": "e3p2i9q",
            "is_submitter": false,
            "link_id": "t3_94zuud",
            "nest_level": 1,
            "no_follow": true,
            "parent_id": "t3_94zuud",
            "permalink": "/r/dirtypenpals/comments/94zuud/22_f4m_your_girlfriend_doesnt_let_you_well_i_could/e3p2i9q/",
            "reply_delay": 7755,
            "retrieved_on": 1537133179,
            "score": 0,
            "send_replies": true,
            "stickied": false,
            "subreddit": "dirtypenpals",
            "subreddit_id": "t5_2sbbv",
            "subreddit_name_prefixed": "r/dirtypenpals",
            "subreddit_type": "public"
        },
        {
            "author": "Groobythegreat",
            "author_created_utc": 1447269299,
            "author_flair_background_color": null,
            "author_flair_css_class": null,
            "author_flair_richtext": [],
            "author_flair_template_id": null,
            "author_flair_text": null,
            "author_flair_text_color": null,
            "author_flair_type": "text",
            "author_fullname": "t2_ry3p7",
            "body": "Check the sidebar of the subreddit.",
            "can_gild": true,
            "collapsed": false,
            "collapsed_reason": null,
            "controversiality": 0,
            "created_utc": 1533556103,
            "distinguished": null,
            "gilded": 0,
            "id": "e3p2rqe",
            "is_submitter": false,
            "link_id": "t3_94zuud",
            "nest_level": 2,
            "no_follow": true,
            "parent_id": "t1_e3p1h2r",
            "permalink": "/r/dirtypenpals/comments/94zuud/22_f4m_your_girlfriend_doesnt_let_you_well_i_could/e3p2rqe/",
            "reply_delay": 2123,
            "retrieved_on": 1537133296,
            "score": 2,
            "send_replies": true,
            "stickied": false,
            "subreddit": "dirtypenpals",
            "subreddit_id": "t5_2sbbv",
            "subreddit_name_prefixed": "r/dirtypenpals",
            "subreddit_type": "public"
        },
        {
            "author": "1petter",
            "author_created_utc": 1479130684,
            "author_flair_background_color": null,
            "author_flair_css_class": null,
            "author_flair_richtext": [],
            "author_flair_template_id": null,
            "author_flair_text": null,
            "author_flair_text_color": null,
            "author_flair_type": "text",
            "author_fullname": "t2_12t2ur",
            "body": "Sorry I\u2019m a mobile user and only logged in in a browser to enable nsfw xD",
            "can_gild": true,
            "collapsed": false,
            "collapsed_reason": null,
            "controversiality": 0,
            "created_utc": 1533560468,
            "distinguished": null,
            "gilded": 0,
            "id": "e3p60bm",
            "is_submitter": false,
            "link_id": "t3_94zuud",
            "nest_level": 3,
            "no_follow": true,
            "parent_id": "t1_e3p2rqe",
            "permalink": "/r/dirtypenpals/comments/94zuud/22_f4m_your_girlfriend_doesnt_let_you_well_i_could/e3p60bm/",
            "reply_delay": 4365,
            "retrieved_on": 1537134821,
            "score": 1,
            "send_replies": true,
            "stickied": false,
            "subreddit": "dirtypenpals",
            "subreddit_id": "t5_2sbbv",
            "subreddit_name_prefixed": "r/dirtypenpals",
            "subreddit_type": "public"
        },
        {
            "author": "dirkdiggleruk99",
            "author_created_utc": 1521291076,
            "author_flair_background_color": null,
            "author_flair_css_class": null,
            "author_flair_richtext": [],
            "author_flair_template_id": null,
            "author_flair_text": null,
            "author_flair_text_color": null,
            "author_flair_type": "text",
            "author_fullname": "t2_11zdgoyr",
            "body": "Would love to play and empty my big balls on u asap bwc m33",
            "can_gild": true,
            "collapsed": false,
            "collapsed_reason": null,
            "controversiality": 0,
            "created_utc": 1533561770,
            "distinguished": null,
            "gilded": 0,
            "id": "e3p74ab",
            "is_submitter": false,
            "link_id": "t3_94zuud",
            "nest_level": 1,
            "no_follow": true,
            "parent_id": "t3_94zuud",
            "permalink": "/r/dirtypenpals/comments/94zuud/22_f4m_your_girlfriend_doesnt_let_you_well_i_could/e3p74ab/",
            "reply_delay": 13830,
            "retrieved_on": 1537135343,
            "score": -1,
            "send_replies": true,
            "stickied": false,
            "subreddit": "dirtypenpals",
            "subreddit_id": "t5_2sbbv",
            "subreddit_name_prefixed": "r/dirtypenpals",
            "subreddit_type": "public"
        },
        {
            "author": "sexysecretaz",
            "author_created_utc": 1533152506,
            "author_flair_background_color": null,
            "author_flair_css_class": null,
            "author_flair_richtext": [],
            "author_flair_template_id": null,
            "author_flair_text": null,
            "author_flair_text_color": null,
            "author_flair_type": "text",
            "author_fullname": "t2_1wdvcglo",
            "body": "My wife is the opposite of you, which makes you more fun! \ud83d\ude08",
            "can_gild": true,
            "collapsed": false,
            "collapsed_reason": null,
            "controversiality": 0,
            "created_utc": 1533572141,
            "distinguished": null,
            "gilded": 0,
            "id": "e3pi24o",
            "is_submitter": false,
            "link_id": "t3_94zuud",
            "nest_level": 1,
            "no_follow": true,
            "parent_id": "t3_94zuud",
            "permalink": "/r/dirtypenpals/comments/94zuud/22_f4m_your_girlfriend_doesnt_let_you_well_i_could/e3pi24o/",
            "reply_delay": 24201,
            "retrieved_on": 1537140433,
            "score": 0,
            "send_replies": true,
            "stickied": false,
            "subreddit": "dirtypenpals",
            "subreddit_id": "t5_2sbbv",
            "subreddit_name_prefixed": "r/dirtypenpals",
            "subreddit_type": "public"
        },
        {
            "author": "TheRibaldCounselor",
            "author_created_utc": 1480447480,
            "author_flair_background_color": null,
            "author_flair_css_class": null,
            "author_flair_richtext": [],
            "author_flair_template_id": null,
            "author_flair_text": null,
            "author_flair_text_color": null,
            "author_flair_type": "text",
            "author_fullname": "t2_136n1q",
            "body": "I try not to advertise my plans to empty my balls \"ASAP\" :)",
            "can_gild": true,
            "collapsed": false,
            "collapsed_reason": null,
            "controversiality": 0,
            "created_utc": 1533572829,
            "distinguished": null,
            "gilded": 0,
            "id": "e3pivci",
            "is_submitter": false,
            "link_id": "t3_94zuud",
            "nest_level": 2,
            "no_follow": true,
            "parent_id": "t1_e3p74ab",
            "permalink": "/r/dirtypenpals/comments/94zuud/22_f4m_your_girlfriend_doesnt_let_you_well_i_could/e3pivci/",
            "reply_delay": 11059,
            "retrieved_on": 1537140825,
            "score": 2,
            "send_replies": true,
            "stickied": false,
            "subreddit": "dirtypenpals",
            "subreddit_id": "t5_2sbbv",
            "subreddit_name_prefixed": "r/dirtypenpals",
            "subreddit_type": "public"
        },
        {
            "author": "TheChooseyMinnow",
            "author_created_utc": 1526455723,
            "author_flair_background_color": null,
            "author_flair_css_class": null,
            "author_flair_richtext": [],
            "author_flair_template_id": null,
            "author_flair_text": null,
            "author_flair_text_color": null,
            "author_flair_type": "text",
            "author_fullname": "t2_1donvy17",
            "body": "What if my girlfriend doesn\u2019t let me wish her into existence?",
            "can_gild": true,
            "collapsed": false,
            "collapsed_reason": null,
            "controversiality": 0,
            "created_utc": 1533574168,
            "distinguished": null,
            "gilded": 0,
            "id": "e3pkfza",
            "is_submitter": false,
            "link_id": "t3_94zuud",
            "nest_level": 1,
            "no_follow": true,
            "parent_id": "t3_94zuud",
            "permalink": "/r/dirtypenpals/comments/94zuud/22_f4m_your_girlfriend_doesnt_let_you_well_i_could/e3pkfza/",
            "reply_delay": 26228,
            "retrieved_on": 1537141551,
            "score": 3,
            "send_replies": true,
            "stickied": false,
            "subreddit": "dirtypenpals",
            "subreddit_id": "t5_2sbbv",
            "subreddit_name_prefixed": "r/dirtypenpals",
            "subreddit_type": "public"
        },
        {
            "author": "fuckyou3000",
            "author_created_utc": 1526635370,
            "author_flair_background_color": null,
            "author_flair_css_class": null,
            "author_flair_richtext": [],
            "author_flair_template_id": null,
            "author_flair_text": null,
            "author_flair_text_color": null,
            "author_flair_type": "text",
            "author_fullname": "t2_1e70uwhr",
            "body": "My girlfriends a stuck up prick. I love girls like you. Pm me",
            "can_gild": true,
            "collapsed": false,
            "collapsed_reason": null,
            "controversiality": 0,
            "created_utc": 1533583685,
            "distinguished": null,
            "gilded": 0,
            "id": "e3pvswe",
            "is_submitter": false,
            "link_id": "t3_94zuud",
            "nest_level": 1,
            "no_follow": true,
            "parent_id": "t3_94zuud",
            "permalink": "/r/dirtypenpals/comments/94zuud/22_f4m_your_girlfriend_doesnt_let_you_well_i_could/e3pvswe/",
            "reply_delay": 35745,
            "retrieved_on": 1537146855,
            "score": 0,
            "send_replies": true,
            "stickied": false,
            "subreddit": "dirtypenpals",
            "subreddit_id": "t5_2sbbv",
            "subreddit_name_prefixed": "r/dirtypenpals",
            "subreddit_type": "public"
        },
        {
            "author": "[deleted]",
            "author_flair_background_color": "",
            "author_flair_css_class": null,
            "author_flair_template_id": null,
            "author_flair_text": null,
            "author_flair_text_color": "dark",
            "body": "That is so hot! I\u2019d love to chat with you!",
            "can_gild": false,
            "collapsed": false,
            "collapsed_reason": null,
            "controversiality": 0,
            "created_utc": 1533584062,
            "distinguished": null,
            "gilded": 0,
            "id": "e3pw9d1",
            "is_submitter": false,
            "link_id": "t3_94zuud",
            "nest_level": 1,
            "no_follow": true,
            "parent_id": "t3_94zuud",
            "permalink": "/r/dirtypenpals/comments/94zuud/22_f4m_your_girlfriend_doesnt_let_you_well_i_could/e3pw9d1/",
            "reply_delay": 36122,
            "retrieved_on": 1537147059,
            "score": 0,
            "send_replies": true,
            "stickied": false,
            "subreddit": "dirtypenpals",
            "subreddit_id": "t5_2sbbv",
            "subreddit_name_prefixed": "r/dirtypenpals",
            "subreddit_type": "public"
        }
    ]
}