{
    "data": [
        {
            "all_awardings": [],
            "associated_award": null,
            "author": "Gwenishavingfun",
            "author_flair_background_color": null,
            "author_flair_css_class": null,
            "author_flair_richtext": [],
            "author_flair_template_id": null,
            "author_flair_text": null,
            "author_flair_text_color": null,
            "author_flair_type": "text",
            "author_fullname": "t2_5797k56h",
            "author_patreon_flair": false,
            "author_premium": false,
            "awarders": [],
            "body": "Very creative",
            "collapsed_because_crowd_control": null,
            "created_utc": 1581379790,
            "gildings": {},
            "id": "fh9f1be",
            "is_submitter": false,
            "link_id": "t3_f1zmau",
            "locked": false,
            "no_follow": true,
            "parent_id": "t3_f1zmau",
            "permalink": "/r/dirtypenpals/comments/f1zmau/29_m4f_transforming_cum/fh9f1be/",
            "retrieved_on": 1581381982,
            "score": 1,
            "send_replies": true,
            "stickied": false,
            "subreddit": "dirtypenpals",
            "subreddit_id": "t5_2sbbv",
            "total_awards_received": 0
        },
        {
            "all_awardings": [],
            "associated_award": null,
            "author": "answeris2",
            "author_flair_background_color": "",
            "author_flair_css_class": "3years",
            "author_flair_richtext": [],
            "author_flair_template_id": null,
            "author_flair_text": "3 Years",
            "author_flair_text_color": "dark",
            "author_flair_type": "text",
            "author_fullname": "t2_7nqr7",
            "author_patreon_flair": false,
            "author_premium": false,
            "awarders": [],
            "body": "Thank you. I am glad it is interesting to other people. What part did you like the most?",
            "collapsed_because_crowd_control": null,
            "created_utc": 1581380024,
            "gildings": {},
            "id": "fh9fdv7",
            "is_submitter": true,
            "link_id": "t3_f1zmau",
            "locked": false,
            "no_follow": true,
            "parent_id": "t1_fh9f1be",
            "permalink": "/r/dirtypenpals/comments/f1zmau/29_m4f_transforming_cum/fh9fdv7/",
            "retrieved_on": 1581382177,
            "score": 1,
            "send_replies": true,
            "stickied": false,
            "subreddit": "dirtypenpals",
            "subreddit_id": "t5_2sbbv",
            "total_awards_received": 0
        },
        {
            "all_awardings": [],
            "associated_award": null,
            "author": "Gwenishavingfun",
            "author_flair_background_color": null,
            "author_flair_css_class": null,
            "author_flair_richtext": [],
            "author_flair_template_id": null,
            "author_flair_text": null,
            "author_flair_text_color": null,
            "author_flair_type": "text",
            "author_fullname": "t2_5797k56h",
            "author_patreon_flair": false,
            "author_premium": false,
            "awarders": [],
            "body": "The mind control aspect of it. Like a subtle hypnosis.",
            "collapsed_because_crowd_control": null,
            "created_utc": 1581479925,
            "gildings": {},
            "id": "fhd8vpp",
            "is_submitter": false,
            "link_id": "t3_f1zmau",
            "locked": false,
            "no_follow": true,
            "parent_id": "t1_fh9fdv7",
            "permalink": "/r/dirtypenpals/comments/f1zmau/29_m4f_transforming_cum/fhd8vpp/",
            "retrieved_on": 1581479926,
            "score": 1,
            "send_replies": true,
            "stickied": false,
            "subreddit": "dirtypenpals",
            "subreddit_id": "t5_2sbbv",
            "total_awards_received": 0
        }
    ]
}