{
    "data": [
        {
            "all_awardings": [],
            "author": "Razzington",
            "author_flair_background_color": null,
            "author_flair_css_class": null,
            "author_flair_richtext": [],
            "author_flair_template_id": null,
            "author_flair_text": null,
            "author_flair_text_color": null,
            "author_flair_type": "text",
            "author_fullname": "t2_27h9x1k3",
            "author_patreon_flair": false,
            "body": "...\n\n\"Here is my asshole, here is my clit\n\nWhen I get all stuffed up\n\nI just shout\n\n'Fuck your cock is so good, its stretching my butt out'\"\n\n...\n\n...\n\n...\n\nI'm sorry...",
            "created_utc": 1560899422,
            "gildings": {},
            "id": "erijq5v",
            "is_submitter": false,
            "link_id": "t3_c299q8",
            "locked": false,
            "no_follow": true,
            "parent_id": "t3_c299q8",
            "permalink": "/r/dirtypenpals/comments/c299q8/25_f4m_im_a_little_butslutt_short_and_thicc/erijq5v/",
            "retrieved_on": 1560899423,
            "score": 5,
            "send_replies": true,
            "stickied": false,
            "subreddit": "dirtypenpals",
            "subreddit_id": "t5_2sbbv",
            "total_awards_received": 0,
            "updated_utc": 1560985820
        },
        {
            "all_awardings": [],
            "author": "CapitalY",
            "author_flair_background_color": null,
            "author_flair_css_class": null,
            "author_flair_richtext": [],
            "author_flair_template_id": null,
            "author_flair_text": null,
            "author_flair_text_color": null,
            "author_flair_type": "text",
            "author_fullname": "t2_5vivd",
            "author_patreon_flair": false,
            "body": "I feel like the syllable count is off on the last verse but maybe it\u2019s just me?\n\nIf it is, here\u2019s my fix.\n\n\u2018Fuck your cock is good, it\u2019s stretching me out\u2019",
            "created_utc": 1560978255,
            "gildings": {},
            "id": "erl4qqu",
            "is_submitter": false,
            "link_id": "t3_c299q8",
            "locked": false,
            "no_follow": true,
            "parent_id": "t1_erijq5v",
            "permalink": "/r/dirtypenpals/comments/c299q8/25_f4m_im_a_little_butslutt_short_and_thicc/erl4qqu/",
            "retrieved_on": 1560978262,
            "score": 2,
            "send_replies": true,
            "stickied": false,
            "subreddit": "dirtypenpals",
            "subreddit_id": "t5_2sbbv",
            "total_awards_received": 0,
            "updated_utc": 1561064657
        }
    ]
}